peakrdl_viz/__about__.py
peakrdl_viz/__init__.py
peakrdl_viz/__peakrdl__.py
peakrdl_viz/design_scanner.py
peakrdl_viz/design_sizer.py
peakrdl_viz/exporter.py
peakrdl_viz/generator.py
peakrdl_viz/sizes.py
peakrdl_viz/templates/field_template.tlv
peakrdl_viz/templates/node_template.tlv
peakrdl_viz/templates/register_template.tlv
peakrdl_viz/templates/timeline_template.tlv
peakrdl_viz/templates/viz_template.tlv
peakrdl_viz-1.0.2.dist-info/METADATA
peakrdl_viz-1.0.2.dist-info/WHEEL
peakrdl_viz-1.0.2.dist-info/entry_points.txt
peakrdl_viz-1.0.2.dist-info/top_level.txt
peakrdl_viz-1.0.2.dist-info/RECORD
